README.md
setup.cfg
setup.py
inxai/__init__.py
inxai/global_metrics.py
inxai/perturbers.py
inxai/segmenters.py
inxaimlflow/__init__.py
inxaimlflow/accelerated_loss.py
inxaimlflow/consistency.py
inxaimlflow/ensemble.py
inxaimlflow/ensemble_exception.py
inxaimlflow/main.py
inxaimlflow/stability.py
inxaimlflow.egg-info/PKG-INFO
inxaimlflow.egg-info/SOURCES.txt
inxaimlflow.egg-info/dependency_links.txt
inxaimlflow.egg-info/requires.txt
inxaimlflow.egg-info/top_level.txt
inxaimlflow/utils/__init__.py
inxaimlflow/utils/scaling.py